[
    {
        "key": "lisan",
        "name": "LISAN Health & Internet",
        "location": {
            "city": "Salvador",
            "state": "Bahia",
            "acronym": "BA"
        },
        "employees": "11 a 20",
        "website": "http://lisan-internet.com",
        "begin_use_php": "",
        "frameworks": [""],
        "tests": [""],
        "other_technologies": [""]
    },
    {
        "key": "compos",
        "name": "COMPOS",
        "location": {
            "city": "Salvador",
            "state": "Bahia",
            "acronym": "BA"
        },
        "employees": "20 ou mais",
        "website": "compos.com",
        "frameworks": [""],
        "tests": [""],
        "other_technologies": [""]
    },
    {
        "key": "i3",
        "name": "i3 Inovações",
        "location": {
            "city": "Salvador",
            "state": "Bahia",
            "acronym": "BA"
        },
        "employees": "2 a 10",
        "website": "http://i3inovacoes.com/",
        "frameworks": [""],
        "tests": ["Teste de Aceitação"],
        "other_technologies": [""]
    },
    {
        "key": "viva",
        "name": "Viva Inovação",
        "location": {
            "city": "Salvador",
            "state": "Bahia",
            "acronym": "BA"
        },
        "employees": "2 a 10",
        "website": "http://www.vivainovacao.com/",
        "frameworks": [""],
        "tests": ["Teste de Integração", "Teste de Aceitação"],
        "other_technologies": [""]
    },
    {
        "key": "diginet",
        "name": "Grupo Diginet",
        "location": {
            "city": "Salvador",
            "state": "Bahia",
            "acronym": "BA"
        },
        "employees": "20 ou mais",
        "website": "http://www.grupodiginet.com.br/",
        "frameworks": [""],
        "tests": ["Teste de Aceitação"],
        "other_technologies": [""]
    },
    {
        "key": "belt",
        "name": "Belt Soluções",
        "location": {
            "city": "Salvador",
            "state": "Bahia",
            "acronym": "BA"
        },
        "employees": "2 a 10",
        "website": "http://www.beltsolucoes.com.br/",
        "begin_use_php": "",
        "frameworks": [""],
        "tests": ["Teste de Integração", "Teste de Aceitação"],
        "other_technologies": [""]
    },
    {
        "key": "beeweb",
        "name": "BeeWeb",
        "location": {
            "city": "Salvador",
            "state": "Bahia",
            "acronym": "BA"
        },
        "employees": "2 a 10",
        "website": "http://www.beeweb.com.br/",
        "frameworks": [""],
        "tests": ["Teste de Integração", "Teste de Aceitação"],
        "other_technologies": [""]
    },
    {
        "key": "selfhotel",
        "name": "SelfHotel",
        "location": {
            "city": "Salvador",
            "state": "Bahia",
            "acronym": "BA"
        },
        "employees": "2 a 10",
        "website": "http://selfhotel.com.br/",
        "begin_use_php": "",
        "frameworks": [""],
        "tests": ["Teste de Integração", "Teste de Aceitação"],
        "other_technologies": [""]
    },
    {
        "key": "w6",
        "name": "W6 Solutions",
        "location": {
            "city": "Salvador",
            "state": "Bahia",
            "acronym": "BA"
        },
        "employees": "11 a 20",
        "website": "http://www.w6solutions.com.br/",
        "begin_use_php": "",
        "frameworks": [""],
        "tests": ["Teste de Integração", "Teste de Aceitação"],
        "other_technologies": [""]
    },
    {
        "key": "soterotech",
        "name": "Sotero Tech",
        "location": {
            "city": "Lauro de Freitas",
            "state": "Bahia",
            "acronym": "BA"
        },
        "employees": "2 a 10",
        "website": "http://www.soterotech.com.br",
        "frameworks": ["Zend Framework", "Laravel"],
        "tests": [""],
        "other_technologies": [""]
    },
    {
        "key": "ecglobalsolutions",
        "name": "eGlobalsolutions",
        "location": {
            "city": "Salvador",
            "state": "Bahia",
            "acronym": "BA"
        },
        "employees": "20 ou mais",
        "website": "ecglobalsolutions.com",
        "frameworks": ["Zend Framework", "Codeigniter", "Yii"],
        "tests": ["Teste Unitário"],
        "other_technologies": [""]
    },
    {
        "key": "ecglobal",
        "name": "ecglobal",
        "location": {
            "city": "Salvador",
            "state": "Bahia",
            "acronym": "BA"
        },
        "employees": "20 ou mais",
        "website": "http://www.ecglobalnet.com/",
        "frameworks": [""],
        "tests": [""],
        "other_technologies": [""]
    },
    {
        "key": "serpro",
        "name": "Serpro",
        "location": {
            "city": "Salvador",
            "state": "Bahia",
            "acronym": "BA"
        },
        "employees": "20 ou mais",
        "website": "http://serpro.gov.br",
        "frameworks": ["Zend Framework", "Symfony", "Silex", "Laravel"],
        "tests": ["Teste Unitário", "Teste de Aceitação"],
        "other_technologies": [""]
    },
    {
        "key": "focus",
        "name": "Focus Tecnologia em Sistemas",
        "location": {
            "city": "Salvador",
            "state": "Bahia",
            "acronym": "BA"
        },
        "employees": "11 a 20",
        "website": "www.focusts.com.br",
        "frameworks": ["Próprio"],
        "tests": [""],
        "other_technologies": [""]
    },
    {
        "key": "convergence",
        "name": "Convergence Works",
        "location": {
            "city": "Salvador",
            "state": "Bahia",
            "acronym": "BA"
        },
        "employees": "20 ou mais",
        "website": "http://convergence.works",
        "frameworks": ["Symfony", "Silex", "Typo3 CMS"],
        "tests": [""],
        "other_technologies": [""]
    },
    {
        "key": "mederi",
        "name": "Mederi",
        "location": {
            "city": "Feira de Santana",
            "state": "Bahia",
            "acronym": "BA"
        },
        "employees": "20 ou mais",
        "website": "",
        "frameworks": ["Laravel", "Próprio"],
        "tests": [""],
        "other_technologies": [""]
    },
    {
        "key": "solutis",
        "name": "Solutis",
        "location": {
            "city": "Salvador",
            "state": "Bahia",
            "acronym": "BA"
        },
        "employees": "20 ou mais",
        "website": "solutis.com.br",
        "frameworks": ["Symfony", "Silex", "CakePHP", "Slim"],
        "tests": ["Teste Unitário", "Teste de Integração"],
        "other_technologies": [""]
    },
    {
        "key": "ifbaiano",
        "name": "IF Baiano",
        "location": {
            "city": "Salvador",
            "state": "Bahia",
            "acronym": "BA"
        },
        "employees": "20 ou mais",
        "website": "ifbaiano.edu.br",
        "frameworks": ["CakePHP", "Miolo"],
        "tests": [""],
        "other_technologies": [""]
    },
    {
        "key": "eternum",
        "name": "Eternum TI",
        "location": {
            "city": "Salvador",
            "state": "Bahia",
            "acronym": "BA"
        },
        "employees": "2 a 10",
        "website": "http://www.eternumti.com.br",
        "frameworks": ["CakePHP"],
        "tests": [""],
        "other_technologies": [""]
    },
    {
        "key": "lupalina",
        "name": "Lupalina",
        "location": {
            "city": "Feira de Santana",
            "state": "Bahia",
            "acronym": "BA"
        },
        "employees": "20 ou mais",
        "website": "www.lupalina.com.br",
        "frameworks": ["Zend Framework", "Phalcon"],
        "tests": ["Teste Unitário", "Teste de Integração"],
        "other_technologies": [""]
    },
    {
        "key": "linceweb",
        "name": "LinceWeb",
        "location": {
            "city": "Feira de Santana",
            "state": "Bahia",
            "acronym": "BA"
        },
        "employees": "2 a 10",
        "website": "www.linceweb.com.br",
        "frameworks": ["Laravel", "Próprio"],
        "tests": [""],
        "other_technologies": [""]
    },
    {
        "key": "sensorial",
        "name": "Sensorial",
        "location": {
            "city": "Feira de Santana",
            "state": "Bahia",
            "acronym": "BA"
        },
        "employees": "2 a 10",
        "website": "www.sensorial.com.br",
        "frameworks": ["Laravel"],
        "tests": [""],
        "other_technologies": [""]
    },
    {
        "key": "soledade",
        "name": "Soledade Tecnologia",
        "location": {
            "city": "Salvador",
            "state": "Bahia",
            "acronym": "BA"
        },
        "employees": "2 a 10",
        "website": "http://soledadetecnologia.com.br/",
        "frameworks": ["Laravel"],
        "tests": ["Teste Unitário"],
        "other_technologies": [""]
    },
    {
        "key": "simetria",
        "name": "Simetria",
        "location": {
            "city": "Salvador",
            "state": "Bahia",
            "acronym": "BA"
        },
        "employees": "2 a 10",
        "website": "http://simetrianet.com.br/",
        "frameworks": ["Laravel"],
        "tests": ["Teste Unitário"],
        "other_technologies": [""]
    },
    {
        "key": "giusoft",
        "name": "Giusoft",
        "location": {
            "city": "Lauro de Freitas",
            "state": "Bahia",
            "acronym": "BA"
        },
        "employees": "2 a 10",
        "website": "https://www.giusoft.com.br/gadmin/",
        "frameworks": ["Próprio"],
        "tests": [""],
        "other_technologies": [""]
    },
    {
        "key": "vivasalute",
        "name": "Clínica da Obesidade / Viva Salute",
        "location": {
            "city": "Camaçari",
            "state": "Bahia",
            "acronym": "BA"
        },
        "employees": "260",
        "website": "https://www.vivasalute.com.br",
        "frameworks": ["Yii"],
        "tests": [""],
        "other_technologies": [""]
    },
    {
        "key": "doteri",
        "name": "Doteri Tecnologia da Informação",
        "location": {
            "city": "Salvador",
            "state": "Bahia",
            "acronym": "BA"
        },
        "employees": "10",
        "website": "http://www.doteri.com",
        "frameworks": ["Symfony", "Silex"],
        "tests": ["Teste de unidade", "Teste de integração", "Teste de stress"],
        "other_technologies": [""]
    },
    {
        "key": "simplesvet",
        "name": "SimplesVet",
        "location": {
            "city": "Salvador",
            "state": "Bahia",
            "acronym": "BA"
        },
        "employees": "+10",
        "website": "https://www.simples.vet.br",
        "frameworks": ["Slim", "Próprio"],
        "tests": ["Teste de integração", "Teste de aceitação"],
        "other_technologies": ["AngularJS"]
    },
    {
        "key": "avansys",
        "name": "Avansys",
        "location": {
            "city": "Salvador",
            "state": "Bahia",
            "acronym": "BA"
        },
        "employees": "+900",
        "website": "http://www.avansys.com.br/",
        "frameworks": ["Zend Framework"],
        "tests": ["Teste Unitário"],
        "other_technologies": ["Java", "ASP", ".NET"]
    }
]
